revelio_client/__init__.py
revelio_client/cli.py
revelio_client/revelio_client.py
revelio_client-0.1.0.dist-info/LICENSE
revelio_client-0.1.0.dist-info/METADATA
revelio_client-0.1.0.dist-info/WHEEL
revelio_client-0.1.0.dist-info/entry_points.txt
revelio_client-0.1.0.dist-info/top_level.txt
revelio_client-0.1.0.dist-info/RECORD
