Metadata-Version: 2.1
Name: revelio-client
Version: 0.1.0
Summary: Harry Potter CLI :)
Home-page: https://github.com/allanbreyes/revelio_client
Author: Allan Reyes
Author-email: pypi@reyes.sh
License: MIT license
Keywords: revelio-client
Platform: UNKNOWN
Classifier: Development Status :: 2 - Pre-Alpha
Classifier: Intended Audience :: Developers
Classifier: License :: OSI Approved :: MIT License
Classifier: Natural Language :: English
Classifier: Programming Language :: Python :: 3
Classifier: Programming Language :: Python :: 3.5
Classifier: Programming Language :: Python :: 3.6
Classifier: Programming Language :: Python :: 3.7
Classifier: Programming Language :: Python :: 3.8
Requires-Python: >=3.5
Requires-Dist: Click (>=7.0)
